{"page": 250, "lines": [{"ln": 1, "tp": "ayah", "ce": false, "words": ["وَيَسۡتَعۡجِلُونَكَ", "بِٱلسَّيِّئَةِ", "قَبۡلَ", "ٱلۡحَسَنَةِ", "وَقَدۡ", "خَلَتۡ", "مِن"], "ayah_range": {"start": {"surah": 13, "ayah": 6}, "end": {"surah": 13, "ayah": 6}}}, {"ln": 2, "tp": "ayah", "ce": false, "words": ["قَبۡلِهِمُ", "ٱلۡمَثُلَٰتُۗ", "وَإِنَّ", "رَبَّكَ", "لَذُو", "مَغۡفِرَةٖ", "لِّلنَّاسِ", "عَلَىٰ", "ظُلۡمِهِمۡۖ"], "ayah_range": {"start": {"surah": 13, "ayah": 6}, "end": {"surah": 13, "ayah": 6}}}, {"ln": 3, "tp": "ayah", "ce": false, "words": ["وَإِنَّ", "رَبَّكَ", "لَشَدِيدُ", "ٱلۡعِقَابِ", "٦", "وَيَقُولُ", "ٱلَّذِينَ", "كَفَرُواْ", "لَوۡلَآ"], "ayah_range": {"start": {"surah": 13, "ayah": 6}, "end": {"surah": 13, "ayah": 7}}}, {"ln": 4, "tp": "ayah", "ce": false, "words": ["أُنزِلَ", "عَلَيۡهِ", "ءَايَةٞ", "مِّن", "رَّبِّهِۦٓۗ", "إِنَّمَآ", "أَنتَ", "مُنذِرٞۖ", "وَلِكُلِّ", "قَوۡمٍ"], "ayah_range": {"start": {"surah": 13, "ayah": 7}, "end": {"surah": 13, "ayah": 7}}}, {"ln": 5, "tp": "ayah", "ce": false, "words": ["هَادٍ", "٧", "ٱللَّهُ", "يَعۡلَمُ", "مَا", "تَحۡمِلُ", "كُلُّ", "أُنثَىٰ", "وَمَا", "تَغِيضُ", "ٱلۡأَرۡحَامُ"], "ayah_range": {"start": {"surah": 13, "ayah": 7}, "end": {"surah": 13, "ayah": 8}}}, {"ln": 6, "tp": "ayah", "ce": false, "words": ["وَمَا", "تَزۡدَادُۚ", "وَكُلُّ", "شَيۡءٍ", "عِندَهُۥ", "بِمِقۡدَارٍ", "٨", "عَٰلِمُ", "ٱلۡغَيۡبِ"], "ayah_range": {"start": {"surah": 13, "ayah": 8}, "end": {"surah": 13, "ayah": 9}}}, {"ln": 7, "tp": "ayah", "ce": false, "words": ["وَٱلشَّهَٰدَةِ", "ٱلۡكَبِيرُ", "ٱلۡمُتَعَالِ", "٩", "سَوَآءٞ", "مِّنكُم", "مَّنۡ"], "ayah_range": {"start": {"surah": 13, "ayah": 9}, "end": {"surah": 13, "ayah": 10}}}, {"ln": 8, "tp": "ayah", "ce": false, "words": ["أَسَرَّ", "ٱلۡقَوۡلَ", "وَمَن", "جَهَرَ", "بِهِۦ", "وَمَنۡ", "هُوَ", "مُسۡتَخۡفِۭ", "بِٱلَّيۡلِ", "وَسَارِبُۢ"], "ayah_range": {"start": {"surah": 13, "ayah": 10}, "end": {"surah": 13, "ayah": 10}}}, {"ln": 9, "tp": "ayah", "ce": false, "words": ["بِٱلنَّهَارِ", "١٠", "لَهُۥ", "مُعَقِّبَٰتٞ", "مِّنۢ", "بَيۡنِ", "يَدَيۡهِ", "وَمِنۡ", "خَلۡفِهِۦ"], "ayah_range": {"start": {"surah": 13, "ayah": 10}, "end": {"surah": 13, "ayah": 11}}}, {"ln": 10, "tp": "ayah", "ce": false, "words": ["يَحۡفَظُونَهُۥ", "مِنۡ", "أَمۡرِ", "ٱللَّهِۗ", "إِنَّ", "ٱللَّهَ", "لَا", "يُغَيِّرُ", "مَا", "بِقَوۡمٍ", "حَتَّىٰ", "يُغَيِّرُواْ"], "ayah_range": {"start": {"surah": 13, "ayah": 11}, "end": {"surah": 13, "ayah": 11}}}, {"ln": 11, "tp": "ayah", "ce": false, "words": ["مَا", "بِأَنفُسِهِمۡۗ", "وَإِذَآ", "أَرَادَ", "ٱللَّهُ", "بِقَوۡمٖ", "سُوٓءٗا", "فَلَا", "مَرَدَّ", "لَهُۥۚ", "وَمَا"], "ayah_range": {"start": {"surah": 13, "ayah": 11}, "end": {"surah": 13, "ayah": 11}}}, {"ln": 12, "tp": "ayah", "ce": false, "words": ["لَهُم", "مِّن", "دُونِهِۦ", "مِن", "وَالٍ", "١١", "هُوَ", "ٱلَّذِي", "يُرِيكُمُ", "ٱلۡبَرۡقَ", "خَوۡفٗا"], "ayah_range": {"start": {"surah": 13, "ayah": 11}, "end": {"surah": 13, "ayah": 12}}}, {"ln": 13, "tp": "ayah", "ce": false, "words": ["وَطَمَعٗا", "وَيُنشِئُ", "ٱلسَّحَابَ", "ٱلثِّقَالَ", "١٢", "وَيُسَبِّحُ", "ٱلرَّعۡدُ", "بِحَمۡدِهِۦ"], "ayah_range": {"start": {"surah": 13, "ayah": 12}, "end": {"surah": 13, "ayah": 13}}}, {"ln": 14, "tp": "ayah", "ce": false, "words": ["وَٱلۡمَلَٰٓئِكَةُ", "مِنۡ", "خِيفَتِهِۦ", "وَيُرۡسِلُ", "ٱلصَّوَٰعِقَ", "فَيُصِيبُ", "بِهَا"], "ayah_range": {"start": {"surah": 13, "ayah": 13}, "end": {"surah": 13, "ayah": 13}}}, {"ln": 15, "tp": "ayah", "ce": false, "words": ["مَن", "يَشَآءُ", "وَهُمۡ", "يُجَٰدِلُونَ", "فِي", "ٱللَّهِ", "وَهُوَ", "شَدِيدُ", "ٱلۡمِحَالِ", "١٣"], "ayah_range": {"start": {"surah": 13, "ayah": 13}, "end": {"surah": 13, "ayah": 13}}}]}