{"page": 509, "lines": [{"ln": 1, "tp": "ayah", "ce": false, "words": ["وَيَقُولُ", "ٱلَّذِينَ", "ءَامَنُواْ", "لَوۡلَا", "نُزِّلَتۡ", "سُورَةٞۖ", "فَإِذَآ", "أُنزِلَتۡ", "سُورَةٞ"], "ayah_range": {"start": {"surah": 47, "ayah": 20}, "end": {"surah": 47, "ayah": 20}}}, {"ln": 2, "tp": "ayah", "ce": false, "words": ["مُّحۡكَمَةٞ", "وَذُكِرَ", "فِيهَا", "ٱلۡقِتَالُ", "رَأَيۡتَ", "ٱلَّذِينَ", "فِي", "قُلُوبِهِم", "مَّرَضٞ"], "ayah_range": {"start": {"surah": 47, "ayah": 20}, "end": {"surah": 47, "ayah": 20}}}, {"ln": 3, "tp": "ayah", "ce": false, "words": ["يَنظُرُونَ", "إِلَيۡكَ", "نَظَرَ", "ٱلۡمَغۡشِيِّ", "عَلَيۡهِ", "مِنَ", "ٱلۡمَوۡتِۖ", "فَأَوۡلَىٰ", "لَهُمۡ"], "ayah_range": {"start": {"surah": 47, "ayah": 20}, "end": {"surah": 47, "ayah": 20}}}, {"ln": 4, "tp": "ayah", "ce": false, "words": ["٢٠", "طَاعَةٞ", "وَقَوۡلٞ", "مَّعۡرُوفٞۚ", "فَإِذَا", "عَزَمَ", "ٱلۡأَمۡرُ", "فَلَوۡ", "صَدَقُواْ", "ٱللَّهَ"], "ayah_range": {"start": {"surah": 47, "ayah": 20}, "end": {"surah": 47, "ayah": 21}}}, {"ln": 5, "tp": "ayah", "ce": false, "words": ["لَكَانَ", "خَيۡرٗا", "لَّهُمۡ", "٢١", "فَهَلۡ", "عَسَيۡتُمۡ", "إِن", "تَوَلَّيۡتُمۡ", "أَن", "تُفۡسِدُواْ"], "ayah_range": {"start": {"surah": 47, "ayah": 21}, "end": {"surah": 47, "ayah": 22}}}, {"ln": 6, "tp": "ayah", "ce": false, "words": ["فِي", "ٱلۡأَرۡضِ", "وَتُقَطِّعُوٓاْ", "أَرۡحَامَكُمۡ", "٢٢", "أُوْلَٰٓئِكَ", "ٱلَّذِينَ", "لَعَنَهُمُ"], "ayah_range": {"start": {"surah": 47, "ayah": 22}, "end": {"surah": 47, "ayah": 23}}}, {"ln": 7, "tp": "ayah", "ce": false, "words": ["ٱللَّهُ", "فَأَصَمَّهُمۡ", "وَأَعۡمَىٰٓ", "أَبۡصَٰرَهُمۡ", "٢٣", "أَفَلَا", "يَتَدَبَّرُونَ", "ٱلۡقُرۡءَانَ"], "ayah_range": {"start": {"surah": 47, "ayah": 23}, "end": {"surah": 47, "ayah": 24}}}, {"ln": 8, "tp": "ayah", "ce": false, "words": ["أَمۡ", "عَلَىٰ", "قُلُوبٍ", "أَقۡفَالُهَآ", "٢٤", "إِنَّ", "ٱلَّذِينَ", "ٱرۡتَدُّواْ", "عَلَىٰٓ", "أَدۡبَٰرِهِم"], "ayah_range": {"start": {"surah": 47, "ayah": 24}, "end": {"surah": 47, "ayah": 25}}}, {"ln": 9, "tp": "ayah", "ce": false, "words": ["مِّنۢ", "بَعۡدِ", "مَا", "تَبَيَّنَ", "لَهُمُ", "ٱلۡهُدَى", "ٱلشَّيۡطَٰنُ", "سَوَّلَ", "لَهُمۡ", "وَأَمۡلَىٰ"], "ayah_range": {"start": {"surah": 47, "ayah": 25}, "end": {"surah": 47, "ayah": 25}}}, {"ln": 10, "tp": "ayah", "ce": false, "words": ["لَهُمۡ", "٢٥", "ذَٰلِكَ", "بِأَنَّهُمۡ", "قَالُواْ", "لِلَّذِينَ", "كَرِهُواْ", "مَا", "نَزَّلَ", "ٱللَّهُ"], "ayah_range": {"start": {"surah": 47, "ayah": 25}, "end": {"surah": 47, "ayah": 26}}}, {"ln": 11, "tp": "ayah", "ce": false, "words": ["سَنُطِيعُكُمۡ", "فِي", "بَعۡضِ", "ٱلۡأَمۡرِۖ", "وَٱللَّهُ", "يَعۡلَمُ", "إِسۡرَارَهُمۡ", "٢٦"], "ayah_range": {"start": {"surah": 47, "ayah": 26}, "end": {"surah": 47, "ayah": 26}}}, {"ln": 12, "tp": "ayah", "ce": false, "words": ["فَكَيۡفَ", "إِذَا", "تَوَفَّتۡهُمُ", "ٱلۡمَلَٰٓئِكَةُ", "يَضۡرِبُونَ", "وُجُوهَهُمۡ"], "ayah_range": {"start": {"surah": 47, "ayah": 27}, "end": {"surah": 47, "ayah": 27}}}, {"ln": 13, "tp": "ayah", "ce": false, "words": ["وَأَدۡبَٰرَهُمۡ", "٢٧", "ذَٰلِكَ", "بِأَنَّهُمُ", "ٱتَّبَعُواْ", "مَآ", "أَسۡخَطَ", "ٱللَّهَ"], "ayah_range": {"start": {"surah": 47, "ayah": 27}, "end": {"surah": 47, "ayah": 28}}}, {"ln": 14, "tp": "ayah", "ce": false, "words": ["وَكَرِهُواْ", "رِضۡوَٰنَهُۥ", "فَأَحۡبَطَ", "أَعۡمَٰلَهُمۡ", "٢٨", "أَمۡ", "حَسِبَ"], "ayah_range": {"start": {"surah": 47, "ayah": 28}, "end": {"surah": 47, "ayah": 29}}}, {"ln": 15, "tp": "ayah", "ce": false, "words": ["ٱلَّذِينَ", "فِي", "قُلُوبِهِم", "مَّرَضٌ", "أَن", "لَّن", "يُخۡرِجَ", "ٱللَّهُ", "أَضۡغَٰنَهُمۡ", "٢٩"], "ayah_range": {"start": {"surah": 47, "ayah": 29}, "end": {"surah": 47, "ayah": 29}}}]}