{"page": 582, "lines": [{"ln": 1, "tp": "surah_name", "ce": true, "text": "سُورَةُ النبأ"}, {"ln": 2, "tp": "basmallah", "ce": true, "text": "﷽"}, {"ln": 3, "tp": "ayah", "ce": false, "words": ["عَمَّ", "يَتَسَآءَلُونَ", "١", "عَنِ", "ٱلنَّبَإِ", "ٱلۡعَظِيمِ", "٢", "ٱلَّذِي", "هُمۡ", "فِيهِ", "مُخۡتَلِفُونَ", "٣"], "ayah_range": {"start": {"surah": 78, "ayah": 1}, "end": {"surah": 78, "ayah": 3}}}, {"ln": 4, "tp": "ayah", "ce": false, "words": ["كـَلَّا", "سَيَعۡلَمُونَ", "٤", "ثُمَّ", "كـَلَّا", "سَيَعۡلَمُونَ", "٥", "أَلَمۡ", "نَجۡعَلِ", "ٱلۡأَرۡضَ", "مِهَٰدٗا", "٦"], "ayah_range": {"start": {"surah": 78, "ayah": 4}, "end": {"surah": 78, "ayah": 6}}}, {"ln": 5, "tp": "ayah", "ce": false, "words": ["وَٱلۡجِبَالَ", "أَوۡتَادٗا", "٧", "وَخَلَقۡنَٰكُمۡ", "أَزۡوَٰجٗا", "٨", "وَجَعَلۡنَا", "نَوۡمَكُمۡ", "سُبَاتٗا"], "ayah_range": {"start": {"surah": 78, "ayah": 7}, "end": {"surah": 78, "ayah": 9}}}, {"ln": 6, "tp": "ayah", "ce": false, "words": ["٩", "وَجَعَلۡنَا", "ٱلَّيۡلَ", "لِبَاسٗا", "١٠", "وَجَعَلۡنَا", "ٱلنَّهَارَ", "مَعَاشٗا", "١١", "وَبَنَيۡنَا"], "ayah_range": {"start": {"surah": 78, "ayah": 9}, "end": {"surah": 78, "ayah": 12}}}, {"ln": 7, "tp": "ayah", "ce": false, "words": ["فَوۡقَكُمۡ", "سَبۡعٗا", "شِدَادٗا", "١٢", "وَجَعَلۡنَا", "سِرَاجٗا", "وَهَّاجٗا", "١٣", "وَأَنزَلۡنَا", "مِنَ"], "ayah_range": {"start": {"surah": 78, "ayah": 12}, "end": {"surah": 78, "ayah": 14}}}, {"ln": 8, "tp": "ayah", "ce": false, "words": ["ٱلۡمُعۡصِرَٰتِ", "مَآءٗ", "ثَجَّاجٗا", "١٤", "لِّنُخۡرِجَ", "بِهِۦ", "حَبّٗا", "وَنَبَاتٗا", "١٥", "وَجَنَّٰتٍ"], "ayah_range": {"start": {"surah": 78, "ayah": 14}, "end": {"surah": 78, "ayah": 16}}}, {"ln": 9, "tp": "ayah", "ce": false, "words": ["أَلۡفَافًا", "١٦", "إِنَّ", "يَوۡمَ", "ٱلۡفَصۡلِ", "كَانَ", "مِيقَٰتٗا", "١٧", "يَوۡمَ", "يُنفَخُ", "فِي", "ٱلصُّورِ"], "ayah_range": {"start": {"surah": 78, "ayah": 16}, "end": {"surah": 78, "ayah": 18}}}, {"ln": 10, "tp": "ayah", "ce": false, "words": ["فَتَأۡتُونَ", "أَفۡوَاجٗا", "١٨", "وَفُتِحَتِ", "ٱلسَّمَآءُ", "فَكَانَتۡ", "أَبۡوَٰبٗا", "١٩", "وَسُيِّرَتِ"], "ayah_range": {"start": {"surah": 78, "ayah": 18}, "end": {"surah": 78, "ayah": 20}}}, {"ln": 11, "tp": "ayah", "ce": false, "words": ["ٱلۡجِبَالُ", "فَكَانَتۡ", "سَرَابًا", "٢٠", "إِنَّ", "جَهَنَّمَ", "كَانَتۡ", "مِرۡصَادٗا", "٢١", "لِّلطَّٰغِينَ"], "ayah_range": {"start": {"surah": 78, "ayah": 20}, "end": {"surah": 78, "ayah": 22}}}, {"ln": 12, "tp": "ayah", "ce": false, "words": ["مَـَٔابٗا", "٢٢", "لَّٰبِثِينَ", "فِيهَآ", "أَحۡقَابٗا", "٢٣", "لَّا", "يَذُوقُونَ", "فِيهَا", "بَرۡدٗا", "وَلَا", "شَرَابًا"], "ayah_range": {"start": {"surah": 78, "ayah": 22}, "end": {"surah": 78, "ayah": 24}}}, {"ln": 13, "tp": "ayah", "ce": false, "words": ["٢٤", "إِلَّا", "حَمِيمٗا", "وَغَسَّاقٗا", "٢٥", "جَزَآءٗ", "وِفَاقًا", "٢٦", "إِنَّهُمۡ", "كَانُواْ"], "ayah_range": {"start": {"surah": 78, "ayah": 24}, "end": {"surah": 78, "ayah": 27}}}, {"ln": 14, "tp": "ayah", "ce": false, "words": ["لَا", "يَرۡجُونَ", "حِسَابٗا", "٢٧", "وَكَذَّبُواْ", "بِـَٔايَٰتِنَا", "كِذَّابٗا", "٢٨", "وَكُلَّ", "شَيۡءٍ"], "ayah_range": {"start": {"surah": 78, "ayah": 27}, "end": {"surah": 78, "ayah": 29}}}, {"ln": 15, "tp": "ayah", "ce": false, "words": ["أَحۡصَيۡنَٰهُ", "كِتَٰبٗا", "٢٩", "فَذُوقُواْ", "فَلَن", "نَّزِيدَكُمۡ", "إِلَّا", "عَذَابًا", "٣٠"], "ayah_range": {"start": {"surah": 78, "ayah": 29}, "end": {"surah": 78, "ayah": 30}}}]}