{"page": 72, "lines": [{"ln": 1, "tp": "ayah", "ce": false, "words": ["وَمَآ", "أَصَٰبَكُمۡ", "يَوۡمَ", "ٱلۡتَقَى", "ٱلۡجَمۡعَانِ", "فَبِإِذۡنِ", "ٱللَّهِ", "وَلِيَعۡلَمَ", "ٱلۡمُؤۡمِنِينَ"], "ayah_range": {"start": {"surah": 3, "ayah": 166}, "end": {"surah": 3, "ayah": 166}}}, {"ln": 2, "tp": "ayah", "ce": false, "words": ["١٦٦", "وَلِيَعۡلَمَ", "ٱلَّذِينَ", "نَافَقُواْۚ", "وَقِيلَ", "لَهُمۡ", "تَعَالَوۡاْ", "قَٰتِلُواْ", "فِي", "سَبِيلِ", "ٱللَّهِ"], "ayah_range": {"start": {"surah": 3, "ayah": 166}, "end": {"surah": 3, "ayah": 167}}}, {"ln": 3, "tp": "ayah", "ce": false, "words": ["أَوِ", "ٱدۡفَعُواْۖ", "قَالُواْ", "لَوۡ", "نَعۡلَمُ", "قِتَالٗا", "لَّٱتَّبَعۡنَٰكُمۡۗ", "هُمۡ", "لِلۡكُفۡرِ", "يَوۡمَئِذٍ"], "ayah_range": {"start": {"surah": 3, "ayah": 167}, "end": {"surah": 3, "ayah": 167}}}, {"ln": 4, "tp": "ayah", "ce": false, "words": ["أَقۡرَبُ", "مِنۡهُمۡ", "لِلۡإِيمَٰنِۚ", "يَقُولُونَ", "بِأَفۡوَٰهِهِم", "مَّا", "لَيۡسَ", "فِي", "قُلُوبِهِمۡۚ"], "ayah_range": {"start": {"surah": 3, "ayah": 167}, "end": {"surah": 3, "ayah": 167}}}, {"ln": 5, "tp": "ayah", "ce": false, "words": ["وَٱللَّهُ", "أَعۡلَمُ", "بِمَا", "يَكۡتُمُونَ", "١٦٧", "ٱلَّذِينَ", "قَالُواْ", "لِإِخۡوَٰنِهِمۡ", "وَقَعَدُواْ"], "ayah_range": {"start": {"surah": 3, "ayah": 167}, "end": {"surah": 3, "ayah": 168}}}, {"ln": 6, "tp": "ayah", "ce": false, "words": ["لَوۡ", "أَطَاعُونَا", "مَا", "قُتِلُواْۗ", "قُلۡ", "فَٱدۡرَءُواْ", "عَنۡ", "أَنفُسِكُمُ", "ٱلۡمَوۡتَ", "إِن"], "ayah_range": {"start": {"surah": 3, "ayah": 168}, "end": {"surah": 3, "ayah": 168}}}, {"ln": 7, "tp": "ayah", "ce": false, "words": ["كُنتُمۡ", "صَٰدِقِينَ", "١٦٨", "وَلَا", "تَحۡسَبَنَّ", "ٱلَّذِينَ", "قُتِلُواْ", "فِي", "سَبِيلِ", "ٱللَّهِ"], "ayah_range": {"start": {"surah": 3, "ayah": 168}, "end": {"surah": 3, "ayah": 169}}}, {"ln": 8, "tp": "ayah", "ce": false, "words": ["أَمۡوَٰتَۢاۚ", "بَلۡ", "أَحۡيَآءٌ", "عِندَ", "رَبِّهِمۡ", "يُرۡزَقُونَ", "١٦٩", "فَرِحِينَ", "بِمَآ", "ءَاتَىٰهُمُ"], "ayah_range": {"start": {"surah": 3, "ayah": 169}, "end": {"surah": 3, "ayah": 170}}}, {"ln": 9, "tp": "ayah", "ce": false, "words": ["ٱللَّهُ", "مِن", "فَضۡلِهِۦ", "وَيَسۡتَبۡشِرُونَ", "بِٱلَّذِينَ", "لَمۡ", "يَلۡحَقُواْ", "بِهِم"], "ayah_range": {"start": {"surah": 3, "ayah": 170}, "end": {"surah": 3, "ayah": 170}}}, {"ln": 10, "tp": "ayah", "ce": false, "words": ["مِّنۡ", "خَلۡفِهِمۡ", "أَلَّا", "خَوۡفٌ", "عَلَيۡهِمۡ", "وَلَا", "هُمۡ", "يَحۡزَنُونَ", "١٧٠", "۞ يَسۡتَبۡشِرُونَ"], "ayah_range": {"start": {"surah": 3, "ayah": 170}, "end": {"surah": 3, "ayah": 171}}}, {"ln": 11, "tp": "ayah", "ce": false, "words": ["بِنِعۡمَةٖ", "مِّنَ", "ٱللَّهِ", "وَفَضۡلٖ", "وَأَنَّ", "ٱللَّهَ", "لَا", "يُضِيعُ", "أَجۡرَ"], "ayah_range": {"start": {"surah": 3, "ayah": 171}, "end": {"surah": 3, "ayah": 171}}}, {"ln": 12, "tp": "ayah", "ce": false, "words": ["ٱلۡمُؤۡمِنِينَ", "١٧١", "ٱلَّذِينَ", "ٱسۡتَجَابُواْ", "لِلَّهِ", "وَٱلرَّسُولِ", "مِنۢ", "بَعۡدِ", "مَآ", "أَصَابَهُمُ"], "ayah_range": {"start": {"surah": 3, "ayah": 171}, "end": {"surah": 3, "ayah": 172}}}, {"ln": 13, "tp": "ayah", "ce": false, "words": ["ٱلۡقَرۡحُۚ", "لِلَّذِينَ", "أَحۡسَنُواْ", "مِنۡهُمۡ", "وَٱتَّقَوۡاْ", "أَجۡرٌ", "عَظِيمٌ", "١٧٢"], "ayah_range": {"start": {"surah": 3, "ayah": 172}, "end": {"surah": 3, "ayah": 172}}}, {"ln": 14, "tp": "ayah", "ce": false, "words": ["ٱلَّذِينَ", "قَالَ", "لَهُمُ", "ٱلنَّاسُ", "إِنَّ", "ٱلنَّاسَ", "قَدۡ", "جَمَعُواْ", "لَكُمۡ", "فَٱخۡشَوۡهُمۡ"], "ayah_range": {"start": {"surah": 3, "ayah": 173}, "end": {"surah": 3, "ayah": 173}}}, {"ln": 15, "tp": "ayah", "ce": false, "words": ["فَزَادَهُمۡ", "إِيمَٰنٗا", "وَقَالُواْ", "حَسۡبُنَا", "ٱللَّهُ", "وَنِعۡمَ", "ٱلۡوَكِيلُ", "١٧٣"], "ayah_range": {"start": {"surah": 3, "ayah": 173}, "end": {"surah": 3, "ayah": 173}}}]}